biotmed_file_sdk/__init__.py
biotmed_file_sdk/api_client.py
biotmed_file_sdk/api_response.py
biotmed_file_sdk/configuration.py
biotmed_file_sdk/exceptions.py
biotmed_file_sdk/py.typed
biotmed_file_sdk/rest.py
biotmed_file_sdk/api/__init__.py
biotmed_file_sdk/api/file_api_api.py
biotmed_file_sdk/api/health_check_api_api.py
biotmed_file_sdk/api/multiple_part_file_api_api.py
biotmed_file_sdk/models/__init__.py
biotmed_file_sdk/models/complete_multiple_part_upload_file_request.py
biotmed_file_sdk/models/download_file_url_response.py
biotmed_file_sdk/models/error_response.py
biotmed_file_sdk/models/multiple_part_file_upload_part.py
biotmed_file_sdk/models/multiple_part_signed_url.py
biotmed_file_sdk/models/multiple_part_upload_file_generate_signed_urls_request.py
biotmed_file_sdk/models/multiple_part_upload_file_save_e_tag_request.py
biotmed_file_sdk/models/multiple_part_upload_file_url_request.py
biotmed_file_sdk/models/multiple_part_upload_file_url_response.py
biotmed_file_sdk/models/upload_file_url_request.py
biotmed_file_sdk/models/upload_file_url_response.py
biotmed_file_sdk/models/version_response.py
biotmed_file_sdk-2.3.40.dist-info/METADATA
biotmed_file_sdk-2.3.40.dist-info/WHEEL
biotmed_file_sdk-2.3.40.dist-info/top_level.txt
biotmed_file_sdk-2.3.40.dist-info/RECORD
